diagram2code/__init__.py
diagram2code/__main__.py
diagram2code/cli.py
diagram2code/export_graph.py
diagram2code/export_matplotlib.py
diagram2code/export_program.py
diagram2code/labels.py
diagram2code/render_graph.py
diagram2code/schema.py
diagram2code/vision/detect_arrows.py
diagram2code/vision/detect_shapes.py
diagram2code/vision/extract_labels.py
diagram2code/vision/preprocess.py
diagram2code-0.1.4.dist-info/METADATA
diagram2code-0.1.4.dist-info/WHEEL
diagram2code-0.1.4.dist-info/entry_points.txt
diagram2code-0.1.4.dist-info/top_level.txt
diagram2code-0.1.4.dist-info/RECORD
