Metadata-Version: 2.4
Name: diagram2code
Version: 0.1.4
Summary: Convert simple diagram images into runnable code (matplotlib/graphviz).
Author: Kazi Samiul Islam
License-Expression: MIT
Requires-Python: <3.14,>=3.11
Requires-Dist: opencv-python>=4.8
Requires-Dist: numpy>=1.26
Requires-Dist: matplotlib>=3.8
Requires-Dist: networkx>=3.0
Provides-Extra: dev
Requires-Dist: pytest>=7.0; extra == "dev"
Requires-Dist: ruff>=0.5.0; extra == "dev"
Provides-Extra: ocr
Requires-Dist: pytesseract>=0.3.13; extra == "ocr"
Provides-Extra: render
Requires-Dist: matplotlib>=3.8; extra == "render"
Requires-Dist: networkx>=3.0; extra == "render"
